radial_basis_function/__init__.py
radial_basis_function/funcoes_auxiliares.py
radial_basis_function/pseudo_inversa.py
radial_basis_function/rbf.py
radial_basis_function-0.4.0.dist-info/LICENSE
radial_basis_function-0.4.0.dist-info/METADATA
radial_basis_function-0.4.0.dist-info/WHEEL
radial_basis_function-0.4.0.dist-info/RECORD
