Metadata-Version: 2.1
Name: radial-basis-function
Version: 0.4.0
Summary: Radial Basis Function e Multiplicação de Matriz Pseudo-Inversa, para modelos de Regressão e Multi-Classificatórios.
Home-page: https://github.com/VictorVenites/Radial-Basis-Function
License: MIT
Keywords: rbf,Radial Basis Function,Pseudo-Inverse Matrix,Matriz Pseudo-Inversa,Victor Venites
Author: Victor Venites
Author-email: contato@victorvenites.com
Maintainer: Victor Venites
Maintainer-email: contato@victorvenites.com
Requires-Python: >=3.10,<4.0
Classifier: License :: OSI Approved :: MIT License
Classifier: Programming Language :: Python :: 3
Classifier: Programming Language :: Python :: 3.10
Classifier: Programming Language :: Python :: 3.11
Requires-Dist: numpy (>=1.24.3,<2.0.0)
Requires-Dist: pandas (>=2.0.2,<3.0.0)
Project-URL: Documentation, https://github.com/VictorVenites/Radial-Basis-Function
Project-URL: repository, https://github.com/VictorVenites/Radial-Basis-Function
